odoo/addons/shopinvader_elasticsearch/README.rst
odoo/addons/shopinvader_elasticsearch/__init__.py
odoo/addons/shopinvader_elasticsearch/__manifest__.py
odoo/addons/shopinvader_elasticsearch/components/__init__.py
odoo/addons/shopinvader_elasticsearch/components/exporter.py
odoo/addons/shopinvader_elasticsearch/data/ir_export_product.xml
odoo/addons/shopinvader_elasticsearch/demo/backend_demo.xml
odoo/addons/shopinvader_elasticsearch/demo/index_config_demo.xml
odoo/addons/shopinvader_elasticsearch/models/__init__.py
odoo/addons/shopinvader_elasticsearch/models/shopinvader_product.py
odoo/addons/shopinvader_elasticsearch/readme/CONTRIBUTORS.rst
odoo/addons/shopinvader_elasticsearch/readme/DESCRIPTION.rst
odoo/addons/shopinvader_elasticsearch/readme/HISTORY.rst
odoo/addons/shopinvader_elasticsearch/static/description/index.html
odoo/addons/shopinvader_elasticsearch/tests/__init__.py
odoo/addons/shopinvader_elasticsearch/tests/test_shopinvader_elasticsearch.py
odoo/addons/shopinvader_elasticsearch/tests/cassettes/TestElasticsearchBackend.test_10_export_one_product.yaml
odoo/addons/shopinvader_elasticsearch/tests/cassettes/TestElasticsearchBackend.test_20_export_all_products.yaml
odoo/addons/shopinvader_elasticsearch/tests/cassettes/TestElasticsearchBackend.test_30_export_all_categories.yaml
odoo12_addon_shopinvader_elasticsearch-12.0.1.0.3.dist-info/METADATA
odoo12_addon_shopinvader_elasticsearch-12.0.1.0.3.dist-info/WHEEL
odoo12_addon_shopinvader_elasticsearch-12.0.1.0.3.dist-info/top_level.txt
odoo12_addon_shopinvader_elasticsearch-12.0.1.0.3.dist-info/RECORD
